viso_sdk_python-1.1.11.dist-info/AUTHORS
viso_sdk_python-1.1.11.dist-info/WHEEL
viso_sdk_python-1.1.11.dist-info/METADATA
viso_sdk_python-1.1.11.dist-info/COPYING
viso_sdk_python-1.1.11.dist-info/top_level.txt
viso_sdk_python-1.1.11.dist-info/RECORD
tests/smoke/test_dists.py
tests/smoke/__init__.py
tests/meta/__init__.py
tests/meta/test_ensure_type_hints.py
docs/ext/__init__.py
docs/ext/docstrings.py
docs/ext/manager_tmpl.j2
viso_sdk/_version.py
viso_sdk/_version.cpython-38-x86_64-linux-gnu.so
viso_sdk/__init__.py
viso_sdk/__init__.cpython-38-x86_64-linux-gnu.so
viso_sdk/_version.c
viso_sdk/__init__.c
viso_sdk/logging/__init__.py
viso_sdk/logging/logger.cpython-38-x86_64-linux-gnu.so
viso_sdk/logging/__init__.cpython-38-x86_64-linux-gnu.so
viso_sdk/logging/logger.c
viso_sdk/logging/__init__.c
viso_sdk/logging/logger.py
viso_sdk/detection/object.c
viso_sdk/detection/object.cpython-38-x86_64-linux-gnu.so
viso_sdk/detection/object.py
viso_sdk/detection/__init__.py
viso_sdk/detection/__init__.cpython-38-x86_64-linux-gnu.so
viso_sdk/detection/__init__.c
viso_sdk/detection/utils/nms.c
viso_sdk/detection/utils/nms.cpython-38-x86_64-linux-gnu.so
viso_sdk/detection/utils/__init__.py
viso_sdk/detection/utils/nms.py
viso_sdk/detection/utils/__init__.cpython-38-x86_64-linux-gnu.so
viso_sdk/detection/utils/__init__.c
viso_sdk/nodered/flow.cpython-38-x86_64-linux-gnu.so
viso_sdk/nodered/__init__.py
viso_sdk/nodered/flow.c
viso_sdk/nodered/__init__.cpython-38-x86_64-linux-gnu.so
viso_sdk/nodered/flow.py
viso_sdk/nodered/__init__.c
viso_sdk/redis/viso_data.cpython-38-x86_64-linux-gnu.so
viso_sdk/redis/redis_wrapper.py
viso_sdk/redis/viso_data.py
viso_sdk/redis/__init__.py
viso_sdk/redis/__init__.cpython-38-x86_64-linux-gnu.so
viso_sdk/redis/viso_data.c
viso_sdk/redis/redis_wrapper.cpython-38-x86_64-linux-gnu.so
viso_sdk/redis/utils.py
viso_sdk/redis/redis_wrapper.c
viso_sdk/redis/utils.c
viso_sdk/redis/__init__.c
viso_sdk/redis/utils.cpython-38-x86_64-linux-gnu.so
viso_sdk/constants/constants.cpython-38-x86_64-linux-gnu.so
viso_sdk/constants/constants.py
viso_sdk/constants/modules.c
viso_sdk/constants/__init__.py
viso_sdk/constants/modules.cpython-38-x86_64-linux-gnu.so
