Metadata-Version: 2.1
Name: viso-sdk-python
Version: 1.1.11
Summary: VisoSDK: A Python SDK for use in Viso containers
Home-page: https://gitlab.com/TopKamera/03_edge/Base/viso-sdk-python-public.git
Author: support@viso.ai
Author-email: support@viso.ai
License: LGPLv3
Platform: UNKNOWN
Classifier: Development Status :: 5 - Production/Stable
Classifier: Environment :: Console
Classifier: Intended Audience :: System Administrators
Classifier: License :: OSI Approved :: GNU Lesser General Public License v3 (LGPLv3)
Classifier: Natural Language :: English
Classifier: Operating System :: POSIX
Classifier: Programming Language :: Python
Classifier: Programming Language :: Python :: 3
Classifier: Programming Language :: Python :: 3.6
Classifier: Programming Language :: Python :: 3.7
Classifier: Programming Language :: Python :: 3.8
Classifier: Programming Language :: Python :: 3.9
Classifier: Programming Language :: Python :: 3.10
Requires-Python: >=3.6.0
License-File: COPYING
License-File: AUTHORS
Requires-Dist: requests
Requires-Dist: requests-toolbelt
Requires-Dist: setuptools
Requires-Dist: paho-mqtt
Requires-Dist: redis
Requires-Dist: opencv-contrib-python-headless~=4.10.0
Requires-Dist: cython~=3.0.2
Requires-Dist: numpy~=1.26.2
Requires-Dist: six~=1.16.0
Requires-Dist: traceback2~=1.4.0
Requires-Dist: shapely~=2.0.7
